{
  "Ships": [
    {
      "Number of cargo": 194,
      "Name ship": "Bebop",
      "Departure date": "2021-04-11 03:07:31.611",
      "Arrival date": "2021-04-03 01:07:31.611",
      "Type of cargo": "loose"
    },
    {
      "Number of cargo": 185,
      "Name ship": "Vulkan",
      "Departure date": "2021-04-13 07:28:34.494",
      "Arrival date": "2021-04-05 14:28:34.494",
      "Type of cargo": "loose"
    },
    {
      "Number of cargo": 154,
      "Name ship": "Calypso",
      "Departure date": "2021-04-19 21:57:37.195",
      "Arrival date": "2021-04-07 01:57:37.195",
      "Type of cargo": "liquid"
    },
    {
      "Number of cargo": 79,
      "Name ship": "Empress",
      "Departure date": "2021-04-18 08:17:56.406",
      "Arrival date": "2021-04-08 11:17:56.406",
      "Type of cargo": "container"
    },
    {
      "Number of cargo": 104,
      "Name ship": "Bebop",
      "Departure date": "2021-04-20 02:40:12.573",
      "Arrival date": "2021-04-11 10:40:12.573",
      "Type of cargo": "liquid"
    },
    {
      "Number of cargo": 16,
      "Name ship": "Vulkan",
      "Departure date": "2021-04-16 12:21:47.678",
      "Arrival date": "2021-04-14 12:21:47.678",
      "Type of cargo": "container"
    },
    {
      "Number of cargo": 148,
      "Name ship": "Sea Queen",
      "Departure date": "2021-04-28 01:48:04.969",
      "Arrival date": "2021-04-15 17:48:04.969",
      "Type of cargo": "liquid"
    },
    {
      "Number of cargo": 88,
      "Name ship": "Vulkan",
      "Departure date": "2021-04-20 11:28:32.733",
      "Arrival date": "2021-04-16 19:28:32.733",
      "Type of cargo": "loose"
    },
    {
      "Number of cargo": 67,
      "Name ship": "Lenin",
      "Departure date": "2021-04-26 04:29:13.452",
      "Arrival date": "2021-04-17 19:29:13.452",
      "Type of cargo": "container"
    },
    {
      "Number of cargo": 75,
      "Name ship": "Varyag",
      "Departure date": "2021-04-27 11:51:20.773",
      "Arrival date": "2021-04-18 02:51:20.773",
      "Type of cargo": "container"
    },
    {
      "Number of cargo": 153,
      "Name ship": "Colossan",
      "Departure date": "2021-04-24 14:07:34.51",
      "Arrival date": "2021-04-18 05:07:34.51",
      "Type of cargo": "loose"
    },
    {
      "Number of cargo": 127,
      "Name ship": "Inferno",
      "Departure date": "2021-05-04 13:41:41.305",
      "Arrival date": "2021-04-18 16:41:41.305",
      "Type of cargo": "container"
    },
    {
      "Number of cargo": 65,
      "Name ship": "Grossadler",
      "Departure date": "2021-04-27 06:19:28.093",
      "Arrival date": "2021-04-19 03:19:28.093",
      "Type of cargo": "container"
    },
    {
      "Number of cargo": 115,
      "Name ship": "Bismark",
      "Departure date": "2021-04-29 04:23:20.051",
      "Arrival date": "2021-04-19 14:23:20.051",
      "Type of cargo": "liquid"
    },
    {
      "Number of cargo": 149,
      "Name ship": "Gotha",
      "Departure date": "2021-05-08 15:40:47.884",
      "Arrival date": "2021-04-20 00:40:47.884",
      "Type of cargo": "container"
    },
    {
      "Number of cargo": 142,
      "Name ship": "St. George",
      "Departure date": "2021-05-08 02:13:53.421",
      "Arrival date": "2021-04-20 08:13:53.421",
      "Type of cargo": "container"
    },
    {
      "Number of cargo": 39,
      "Name ship": "Empress",
      "Departure date": "2021-04-23 00:41:09.854",
      "Arrival date": "2021-04-21 09:41:09.854",
      "Type of cargo": "loose"
    },
    {
      "Number of cargo": 162,
      "Name ship": "Vulkan",
      "Departure date": "2021-05-11 21:26:15.946",
      "Arrival date": "2021-04-21 15:26:15.946",
      "Type of cargo": "container"
    },
    {
      "Number of cargo": 192,
      "Name ship": "Aurora",
      "Departure date": "2021-05-07 22:11:22.984",
      "Arrival date": "2021-04-21 22:11:22.984",
      "Type of cargo": "liquid"
    },
    {
      "Number of cargo": 63,
      "Name ship": "Colossan",
      "Departure date": "2021-04-25 21:47:55.322",
      "Arrival date": "2021-04-23 06:47:55.322",
      "Type of cargo": "loose"
    },
    {
      "Number of cargo": 176,
      "Name ship": "Alexandria",
      "Departure date": "2021-05-08 09:20:41.624",
      "Arrival date": "2021-04-23 17:20:41.624",
      "Type of cargo": "liquid"
    },
    {
      "Number of cargo": 65,
      "Name ship": "Varyag",
      "Departure date": "2021-04-29 09:57:26.716",
      "Arrival date": "2021-04-23 23:57:26.716",
      "Type of cargo": "liquid"
    },
    {
      "Number of cargo": 193,
      "Name ship": "St. George",
      "Departure date": "2021-05-19 20:36:24.793",
      "Arrival date": "2021-04-25 17:36:24.793",
      "Type of cargo": "container"
    },
    {
      "Number of cargo": 99,
      "Name ship": "Varyag",
      "Departure date": "2021-04-29 23:13:27.152",
      "Arrival date": "2021-04-25 20:13:27.152",
      "Type of cargo": "loose"
    },
    {
      "Number of cargo": 188,
      "Name ship": "Aurora",
      "Departure date": "2021-05-20 20:14:01.326",
      "Arrival date": "2021-04-27 08:14:01.326",
      "Type of cargo": "container"
    },
    {
      "Number of cargo": 158,
      "Name ship": "Sea Queen",
      "Departure date": "2021-05-17 05:42:40.681",
      "Arrival date": "2021-04-27 11:42:40.681",
      "Type of cargo": "container"
    },
    {
      "Number of cargo": 163,
      "Name ship": "Varyag",
      "Departure date": "2021-05-11 03:57:41.267",
      "Arrival date": "2021-04-27 13:57:41.267",
      "Type of cargo": "liquid"
    },
    {
      "Number of cargo": 113,
      "Name ship": "Lenin",
      "Departure date": "2021-05-03 16:46:27.138",
      "Arrival date": "2021-04-28 23:46:27.138",
      "Type of cargo": "loose"
    },
    {
      "Number of cargo": 127,
      "Name ship": "Titanic",
      "Departure date": "2021-05-15 06:15:11.05",
      "Arrival date": "2021-04-29 09:15:11.05",
      "Type of cargo": "container"
    },
    {
      "Number of cargo": 35,
      "Name ship": "Bebop",
      "Departure date": "2021-04-30 22:08:01.548",
      "Arrival date": "2021-04-29 11:08:01.548",
      "Type of cargo": "loose"
    }
  ]
}